novauniverse/__init__.py
novauniverse/configuration.py
novauniverse/errors.py
novauniverse/event_client.py
novauniverse/info.py
novauniverse/api/__init__.py
novauniverse/api/cdn.py
novauniverse/api/endpoints.py
novauniverse/api/errors.py
novauniverse/events/__init__.py
novauniverse/events/client_ready.py
novauniverse/events/player_join.py
novauniverse/events/player_leave.py
novauniverse/interfaces/__init__.py
novauniverse/interfaces/stats/__init__.py
novauniverse/interfaces/stats/discord/__init__.py
novauniverse/interfaces/stats/discord/discord_stats.py
novauniverse/interfaces/stats/server/__init__.py
novauniverse/interfaces/stats/server/global_.py
novauniverse/interfaces/stats/server/nova_online_player.py
novauniverse/interfaces/stats/server/nova_server.py
novauniverse/interfaces/stats/server/player_preview.py
novauniverse/interfaces/stats/server/server_info.py
novauniverse/interfaces/stats/server/system.py
novauniverse/interfaces/tournaments/__init__.py
novauniverse/interfaces/tournaments/mcf/__init__.py
novauniverse/interfaces/tournaments/mcf/mcf_tournament.py
novauniverse/interfaces/tournaments/nova_games/__init__.py
novauniverse/interfaces/tournaments/nova_games/nova_games_tournament.py
novauniverse/objects/__init__.py
novauniverse/objects/nova_dataclass.py
novauniverse/objects/nova_player.py
novauniverse/objects/order_by.py
novauniverse/objects/timestamp.py
novauniverse/objects/tournaments/__init__.py
novauniverse/objects/tournaments/tournament_player.py
novauniverse/objects/tournaments/tournament_team.py
novauniverse/utils/__init__.py
novauniverse/utils/search.py
novauniverse-2.1.3.dist-info/METADATA
novauniverse-2.1.3.dist-info/WHEEL
novauniverse-2.1.3.dist-info/top_level.txt
novauniverse-2.1.3.dist-info/RECORD
