Metadata-Version: 2.1
Name: novauniverse
Version: 2.1.3
Summary: A modern & maintained wrapper for the Nova Universe API written in 🐍 Python.
Author-email: Goldy <goldy@devgoldy.me>
Project-URL: GitHub, https://github.com/NovaUniverse/NovaUniverse.py
Project-URL: BugTracker, https://github.com/NovaUniverse/NovaUniverse.py/issues
Project-URL: ChangeLog, https://github.com/NovaUniverse/NovaUniverse.py/blob/main/CHANGELOG.rst
Keywords: novauniverse,minecraft novauniverse,nova universe,mc novauniverse
Classifier: Operating System :: Microsoft :: Windows :: Windows 11
Classifier: Operating System :: Microsoft :: Windows :: Windows 10
Classifier: Operating System :: POSIX :: Linux
Classifier: License :: OSI Approved :: MIT License
Classifier: Programming Language :: Python :: 3.8
Classifier: Programming Language :: Python :: 3.9
Classifier: Programming Language :: Python :: 3.10
Classifier: Programming Language :: Python :: 3.11
Requires-Python: >=3.7
Requires-Dist: requests
Requires-Dist: devgoldyutils (>=2.4.3)
Requires-Dist: prettyprinter
Requires-Dist: python-decouple (>=3.8)
Requires-Dist: importlib-metadata ; python_version < "3.8"
Provides-Extra: dev
Requires-Dist: ruff ; extra == 'dev'
Requires-Dist: Sphinx ; extra == 'dev'
Requires-Dist: furo ; extra == 'dev'
Requires-Dist: pytest ; extra == 'dev'
Requires-Dist: pytest-cov ; extra == 'dev'
